[{"name":"blue-0","x":0,"y":0,"width":32,"height":32},{"name":"blue-0-pushed","x":0,"y":33,"width":32,"height":32},{"name":"blue-1","x":33,"y":0,"width":32,"height":32},{"name":"blue-1-pushed","x":33,"y":33,"width":32,"height":32},{"name":"blue-2","x":0,"y":66,"width":32,"height":32},{"name":"blue-2-pushed","x":33,"y":66,"width":32,"height":32},{"name":"blue-3","x":66,"y":0,"width":32,"height":32},{"name":"blue-3-pushed","x":66,"y":33,"width":32,"height":32},{"name":"blue-4","x":66,"y":66,"width":32,"height":32},{"name":"blue-4-pushed","x":0,"y":99,"width":32,"height":32},{"name":"blue-5","x":33,"y":99,"width":32,"height":32},{"name":"blue-5-pushed","x":66,"y":99,"width":32,"height":32},{"name":"blue-6","x":99,"y":0,"width":32,"height":32},{"name":"blue-6-pushed","x":99,"y":33,"width":32,"height":32},{"name":"blue-7","x":99,"y":66,"width":32,"height":32},{"name":"blue-7-pushed","x":99,"y":99,"width":32,"height":32},{"name":"blue-8","x":0,"y":132,"width":32,"height":32},{"name":"blue-8-pushed","x":33,"y":132,"width":32,"height":32},{"name":"blue-9","x":66,"y":132,"width":32,"height":32},{"name":"blue-9-pushed","x":99,"y":132,"width":32,"height":32},{"name":"blue-A","x":132,"y":0,"width":32,"height":32},{"name":"blue-A-pushed","x":132,"y":33,"width":32,"height":32},{"name":"blue-!arrowdown","x":132,"y":66,"width":32,"height":32},{"name":"blue-!arrowdown-pushed","x":132,"y":99,"width":32,"height":32},{"name":"blue-!arrowleft","x":132,"y":132,"width":32,"height":32},{"name":"blue-!arrowleft-pushed","x":0,"y":165,"width":32,"height":32},{"name":"blue-!arrowright","x":33,"y":165,"width":32,"height":32},{"name":"blue-!arrowright-pushed","x":66,"y":165,"width":32,"height":32},{"name":"blue-!arrowup","x":99,"y":165,"width":32,"height":32},{"name":"blue-!arrowup-pushed","x":132,"y":165,"width":32,"height":32},{"name":"blue-B","x":165,"y":0,"width":32,"height":32},{"name":"blue-!blank","x":165,"y":33,"width":32,"height":32},{"name":"blue-blank-pushed","x":165,"y":66,"width":32,"height":32},{"name":"blue-B-pushed","x":165,"y":99,"width":32,"height":32},{"name":"blue-C","x":165,"y":132,"width":32,"height":32},{"name":"blue-C-pushed","x":165,"y":165,"width":32,"height":32},{"name":"blue-D","x":0,"y":198,"width":32,"height":32},{"name":"blue-D-pushed","x":33,"y":198,"width":32,"height":32},{"name":"blue-E","x":66,"y":198,"width":32,"height":32},{"name":"blue-E-pushed","x":99,"y":198,"width":32,"height":32},{"name":"blue-F","x":132,"y":198,"width":32,"height":32},{"name":"blue-F-pushed","x":165,"y":198,"width":32,"height":32},{"name":"blue-G","x":198,"y":0,"width":32,"height":32},{"name":"blue-G-pushed","x":198,"y":33,"width":32,"height":32},{"name":"blue-H","x":198,"y":66,"width":32,"height":32},{"name":"blue-H-pushed","x":198,"y":99,"width":32,"height":32},{"name":"blue-I","x":198,"y":132,"width":32,"height":32},{"name":"blue-I-pushed","x":198,"y":165,"width":32,"height":32},{"name":"blue-J","x":198,"y":198,"width":32,"height":32},{"name":"blue-J-pushed","x":0,"y":231,"width":32,"height":32},{"name":"blue-K","x":33,"y":231,"width":32,"height":32},{"name":"blue-K-pushed","x":66,"y":231,"width":32,"height":32},{"name":"blue-L","x":99,"y":231,"width":32,"height":32},{"name":"blue-L-pushed","x":132,"y":231,"width":32,"height":32},{"name":"blue-M","x":165,"y":231,"width":32,"height":32},{"name":"blue-M-pushed","x":198,"y":231,"width":32,"height":32},{"name":"blue-N","x":231,"y":0,"width":32,"height":32},{"name":"blue-N-pushed","x":231,"y":33,"width":32,"height":32},{"name":"blue-O","x":231,"y":66,"width":32,"height":32},{"name":"blue-O-pushed","x":231,"y":99,"width":32,"height":32},{"name":"blue-P","x":231,"y":132,"width":32,"height":32},{"name":"blue-P-pushed","x":231,"y":165,"width":32,"height":32},{"name":"blue-Q","x":231,"y":198,"width":32,"height":32},{"name":"blue-Q-pushed","x":231,"y":231,"width":32,"height":32},{"name":"blue-R","x":0,"y":264,"width":32,"height":32},{"name":"blue-R-pushed","x":33,"y":264,"width":32,"height":32},{"name":"blue-S","x":66,"y":264,"width":32,"height":32},{"name":"blue-S-pushed","x":99,"y":264,"width":32,"height":32},{"name":"blue-!square","x":132,"y":264,"width":32,"height":32},{"name":"blue-square-pushed","x":165,"y":264,"width":32,"height":32},{"name":"blue-T","x":198,"y":264,"width":32,"height":32},{"name":"blue-T-pushed","x":231,"y":264,"width":32,"height":32},{"name":"blue-!triangle","x":264,"y":0,"width":32,"height":32},{"name":"blue-triangle-pushed","x":264,"y":33,"width":32,"height":32},{"name":"blue-U","x":264,"y":66,"width":32,"height":32},{"name":"blue-U-pushed","x":264,"y":99,"width":32,"height":32},{"name":"blue-V","x":264,"y":132,"width":32,"height":32},{"name":"blue-V-pushed","x":264,"y":165,"width":32,"height":32},{"name":"blue-W","x":264,"y":198,"width":32,"height":32},{"name":"blue-W-pushed","x":264,"y":231,"width":32,"height":32},{"name":"blue-X","x":264,"y":264,"width":32,"height":32},{"name":"blue-X-pushed","x":0,"y":297,"width":32,"height":32},{"name":"blue-Y","x":33,"y":297,"width":32,"height":32},{"name":"blue-Y-pushed","x":66,"y":297,"width":32,"height":32},{"name":"blue-Z","x":99,"y":297,"width":32,"height":32},{"name":"blue-Z-pushed","x":132,"y":297,"width":32,"height":32},{"name":"green-0","x":165,"y":297,"width":32,"height":32},{"name":"green-0-pushed","x":198,"y":297,"width":32,"height":32},{"name":"green-1","x":231,"y":297,"width":32,"height":32},{"name":"green-1-pushed","x":264,"y":297,"width":32,"height":32},{"name":"green-2","x":297,"y":0,"width":32,"height":32},{"name":"green-2-pushed","x":297,"y":33,"width":32,"height":32},{"name":"green-3","x":297,"y":66,"width":32,"height":32},{"name":"green-3-pushed","x":297,"y":99,"width":32,"height":32},{"name":"green-4","x":297,"y":132,"width":32,"height":32},{"name":"green-4-pushed","x":297,"y":165,"width":32,"height":32},{"name":"green-5","x":297,"y":198,"width":32,"height":32},{"name":"green-5-pushed","x":297,"y":231,"width":32,"height":32},{"name":"green-6","x":297,"y":264,"width":32,"height":32},{"name":"green-6-pushed","x":297,"y":297,"width":32,"height":32},{"name":"green-7","x":0,"y":330,"width":32,"height":32},{"name":"green-7-pushed","x":33,"y":330,"width":32,"height":32},{"name":"green-8","x":66,"y":330,"width":32,"height":32},{"name":"green-8-pushed","x":99,"y":330,"width":32,"height":32},{"name":"green-9","x":132,"y":330,"width":32,"height":32},{"name":"green-9-pushed","x":165,"y":330,"width":32,"height":32},{"name":"green-A","x":198,"y":330,"width":32,"height":32},{"name":"green-A-pushed","x":231,"y":330,"width":32,"height":32},{"name":"green-!arrowdown","x":264,"y":330,"width":32,"height":32},{"name":"green-!arrowdown-pushed","x":297,"y":330,"width":32,"height":32},{"name":"green-!arrowleft","x":330,"y":0,"width":32,"height":32},{"name":"green-!arrowleft-pushed","x":330,"y":33,"width":32,"height":32},{"name":"green-!arrowright","x":330,"y":66,"width":32,"height":32},{"name":"green-!arrowright-pushed","x":330,"y":99,"width":32,"height":32},{"name":"green-!arrowup","x":330,"y":132,"width":32,"height":32},{"name":"green-!arrowup-pushed","x":330,"y":165,"width":32,"height":32},{"name":"green-B","x":330,"y":198,"width":32,"height":32},{"name":"green-!blank","x":330,"y":231,"width":32,"height":32},{"name":"green-blank-pushed","x":330,"y":264,"width":32,"height":32},{"name":"green-B-pushed","x":330,"y":297,"width":32,"height":32},{"name":"green-C","x":330,"y":330,"width":32,"height":32},{"name":"green-C-pushed","x":0,"y":363,"width":32,"height":32},{"name":"green-D","x":33,"y":363,"width":32,"height":32},{"name":"green-D-pushed","x":66,"y":363,"width":32,"height":32},{"name":"green-E","x":99,"y":363,"width":32,"height":32},{"name":"green-E-pushed","x":132,"y":363,"width":32,"height":32},{"name":"green-F","x":165,"y":363,"width":32,"height":32},{"name":"green-F-pushed","x":198,"y":363,"width":32,"height":32},{"name":"green-G","x":231,"y":363,"width":32,"height":32},{"name":"green-G-pushed","x":264,"y":363,"width":32,"height":32},{"name":"green-H","x":297,"y":363,"width":32,"height":32},{"name":"green-H-pushed","x":330,"y":363,"width":32,"height":32},{"name":"green-I","x":363,"y":0,"width":32,"height":32},{"name":"green-I-pushed","x":363,"y":33,"width":32,"height":32},{"name":"green-J","x":363,"y":66,"width":32,"height":32},{"name":"green-J-pushed","x":363,"y":99,"width":32,"height":32},{"name":"green-K","x":363,"y":132,"width":32,"height":32},{"name":"green-K-pushed","x":363,"y":165,"width":32,"height":32},{"name":"green-L","x":363,"y":198,"width":32,"height":32},{"name":"green-L-pushed","x":363,"y":231,"width":32,"height":32},{"name":"green-M","x":363,"y":264,"width":32,"height":32},{"name":"green-M-pushed","x":363,"y":297,"width":32,"height":32},{"name":"green-N","x":363,"y":330,"width":32,"height":32},{"name":"green-N-pushed","x":363,"y":363,"width":32,"height":32},{"name":"green-O","x":0,"y":396,"width":32,"height":32},{"name":"green-O-pushed","x":33,"y":396,"width":32,"height":32},{"name":"green-P","x":66,"y":396,"width":32,"height":32},{"name":"green-P-pushed","x":99,"y":396,"width":32,"height":32},{"name":"green-Q","x":132,"y":396,"width":32,"height":32},{"name":"green-Q-pushed","x":165,"y":396,"width":32,"height":32},{"name":"green-R","x":198,"y":396,"width":32,"height":32},{"name":"green-R-pushed","x":231,"y":396,"width":32,"height":32},{"name":"green-S","x":264,"y":396,"width":32,"height":32},{"name":"green-S-pushed","x":297,"y":396,"width":32,"height":32},{"name":"green-!square","x":330,"y":396,"width":32,"height":32},{"name":"green-square-pushed","x":363,"y":396,"width":32,"height":32},{"name":"green-T","x":396,"y":0,"width":32,"height":32},{"name":"green-T-pushed","x":396,"y":33,"width":32,"height":32},{"name":"green-!triangle","x":396,"y":66,"width":32,"height":32},{"name":"green-triangle-pushed","x":396,"y":99,"width":32,"height":32},{"name":"green-U","x":396,"y":132,"width":32,"height":32},{"name":"green-U-pushed","x":396,"y":165,"width":32,"height":32},{"name":"green-V","x":396,"y":198,"width":32,"height":32},{"name":"green-V-pushed","x":396,"y":231,"width":32,"height":32},{"name":"green-W","x":396,"y":264,"width":32,"height":32},{"name":"green-W-pushed","x":396,"y":297,"width":32,"height":32},{"name":"green-X","x":396,"y":330,"width":32,"height":32},{"name":"green-X-pushed","x":396,"y":363,"width":32,"height":32},{"name":"green-Y","x":396,"y":396,"width":32,"height":32},{"name":"green-Y-pushed","x":0,"y":429,"width":32,"height":32},{"name":"green-Z","x":33,"y":429,"width":32,"height":32},{"name":"green-Z-pushed","x":66,"y":429,"width":32,"height":32},{"name":"red-0","x":99,"y":429,"width":32,"height":32},{"name":"red-0-pushed","x":132,"y":429,"width":32,"height":32},{"name":"red-1","x":165,"y":429,"width":32,"height":32},{"name":"red-1-pushed","x":198,"y":429,"width":32,"height":32},{"name":"red-2","x":231,"y":429,"width":32,"height":32},{"name":"red-2-pushed","x":264,"y":429,"width":32,"height":32},{"name":"red-3","x":297,"y":429,"width":32,"height":32},{"name":"red-3-pushed","x":330,"y":429,"width":32,"height":32},{"name":"red-4","x":363,"y":429,"width":32,"height":32},{"name":"red-4-pushed","x":396,"y":429,"width":32,"height":32},{"name":"red-5","x":429,"y":0,"width":32,"height":32},{"name":"red-5-pushed","x":429,"y":33,"width":32,"height":32},{"name":"red-6","x":429,"y":66,"width":32,"height":32},{"name":"red-6-pushed","x":429,"y":99,"width":32,"height":32},{"name":"red-7","x":429,"y":132,"width":32,"height":32},{"name":"red-7-pushed","x":429,"y":165,"width":32,"height":32},{"name":"red-8","x":429,"y":198,"width":32,"height":32},{"name":"red-8-pushed","x":429,"y":231,"width":32,"height":32},{"name":"red-9","x":429,"y":264,"width":32,"height":32},{"name":"red-9-pushed","x":429,"y":297,"width":32,"height":32},{"name":"red-A","x":429,"y":330,"width":32,"height":32},{"name":"red-A-pushed","x":429,"y":363,"width":32,"height":32},{"name":"red-!arrowdown","x":429,"y":396,"width":32,"height":32},{"name":"red-!arrowdown-pushed","x":429,"y":429,"width":32,"height":32},{"name":"red-!arrowleft","x":0,"y":462,"width":32,"height":32},{"name":"red-!arrowleft-pushed","x":33,"y":462,"width":32,"height":32},{"name":"red-!arrowright","x":66,"y":462,"width":32,"height":32},{"name":"red-!arrowright-pushed","x":99,"y":462,"width":32,"height":32},{"name":"red-!arrowup","x":132,"y":462,"width":32,"height":32},{"name":"red-!arrowup-pushed","x":165,"y":462,"width":32,"height":32},{"name":"red-B","x":198,"y":462,"width":32,"height":32},{"name":"red-!blank","x":231,"y":462,"width":32,"height":32},{"name":"red-blank-pushed","x":264,"y":462,"width":32,"height":32},{"name":"red-B-pushed","x":297,"y":462,"width":32,"height":32},{"name":"red-C","x":330,"y":462,"width":32,"height":32},{"name":"red-C-pushed","x":363,"y":462,"width":32,"height":32},{"name":"red-D","x":396,"y":462,"width":32,"height":32},{"name":"red-D-pushed","x":429,"y":462,"width":32,"height":32},{"name":"red-E","x":462,"y":0,"width":32,"height":32},{"name":"red-E-pushed","x":462,"y":33,"width":32,"height":32},{"name":"red-F","x":462,"y":66,"width":32,"height":32},{"name":"red-F-pushed","x":462,"y":99,"width":32,"height":32},{"name":"red-G","x":462,"y":132,"width":32,"height":32},{"name":"red-G-pushed","x":462,"y":165,"width":32,"height":32},{"name":"red-H","x":462,"y":198,"width":32,"height":32},{"name":"red-H-pushed","x":462,"y":231,"width":32,"height":32},{"name":"red-I","x":462,"y":264,"width":32,"height":32},{"name":"red-I-pushed","x":462,"y":297,"width":32,"height":32},{"name":"red-J","x":462,"y":330,"width":32,"height":32},{"name":"red-J-pushed","x":462,"y":363,"width":32,"height":32},{"name":"red-K","x":462,"y":396,"width":32,"height":32},{"name":"red-K-pushed","x":462,"y":429,"width":32,"height":32},{"name":"red-L","x":462,"y":462,"width":32,"height":32},{"name":"red-L-pushed","x":0,"y":495,"width":32,"height":32},{"name":"red-M","x":33,"y":495,"width":32,"height":32},{"name":"red-M-pushed","x":66,"y":495,"width":32,"height":32},{"name":"red-N","x":99,"y":495,"width":32,"height":32},{"name":"red-N-pushed","x":132,"y":495,"width":32,"height":32},{"name":"red-O","x":165,"y":495,"width":32,"height":32},{"name":"red-O-pushed","x":198,"y":495,"width":32,"height":32},{"name":"red-P","x":231,"y":495,"width":32,"height":32},{"name":"red-P-pushed","x":264,"y":495,"width":32,"height":32},{"name":"red-Q","x":297,"y":495,"width":32,"height":32},{"name":"red-Q-pushed","x":330,"y":495,"width":32,"height":32},{"name":"red-R","x":363,"y":495,"width":32,"height":32},{"name":"red-R-pushed","x":396,"y":495,"width":32,"height":32},{"name":"red-S","x":429,"y":495,"width":32,"height":32},{"name":"red-S-pushed","x":462,"y":495,"width":32,"height":32},{"name":"red-!square","x":495,"y":0,"width":32,"height":32},{"name":"red-square-pushed","x":495,"y":33,"width":32,"height":32},{"name":"red-T","x":495,"y":66,"width":32,"height":32},{"name":"red-T-pushed","x":495,"y":99,"width":32,"height":32},{"name":"red-!triangle","x":495,"y":132,"width":32,"height":32},{"name":"red-triangle-pushed","x":495,"y":165,"width":32,"height":32},{"name":"red-U","x":495,"y":198,"width":32,"height":32},{"name":"red-U-pushed","x":495,"y":231,"width":32,"height":32},{"name":"red-V","x":495,"y":264,"width":32,"height":32},{"name":"red-V-pushed","x":495,"y":297,"width":32,"height":32},{"name":"red-W","x":495,"y":330,"width":32,"height":32},{"name":"red-W-pushed","x":495,"y":363,"width":32,"height":32},{"name":"red-X","x":495,"y":396,"width":32,"height":32},{"name":"red-X-pushed","x":495,"y":429,"width":32,"height":32},{"name":"red-Y","x":495,"y":462,"width":32,"height":32},{"name":"red-Y-pushed","x":495,"y":495,"width":32,"height":32},{"name":"red-Z","x":0,"y":528,"width":32,"height":32},{"name":"red-Z-pushed","x":33,"y":528,"width":32,"height":32},{"name":"silver-0","x":66,"y":528,"width":32,"height":32},{"name":"silver-0-pushed","x":99,"y":528,"width":32,"height":32},{"name":"silver-1","x":132,"y":528,"width":32,"height":32},{"name":"silver-1-pushed","x":165,"y":528,"width":32,"height":32},{"name":"silver-2","x":198,"y":528,"width":32,"height":32},{"name":"silver-2-pushed","x":231,"y":528,"width":32,"height":32},{"name":"silver-3","x":264,"y":528,"width":32,"height":32},{"name":"silver-3-pushed","x":297,"y":528,"width":32,"height":32},{"name":"silver-4","x":330,"y":528,"width":32,"height":32},{"name":"silver-4-pushed","x":363,"y":528,"width":32,"height":32},{"name":"silver-5","x":396,"y":528,"width":32,"height":32},{"name":"silver-5-pushed","x":429,"y":528,"width":32,"height":32},{"name":"silver-6","x":462,"y":528,"width":32,"height":32},{"name":"silver-6-pushed","x":495,"y":528,"width":32,"height":32},{"name":"silver-7","x":528,"y":0,"width":32,"height":32},{"name":"silver-7-pushed","x":528,"y":33,"width":32,"height":32},{"name":"silver-8","x":528,"y":66,"width":32,"height":32},{"name":"silver-8-pushed","x":528,"y":99,"width":32,"height":32},{"name":"silver-9","x":528,"y":132,"width":32,"height":32},{"name":"silver-9-pushed","x":528,"y":165,"width":32,"height":32},{"name":"silver-A","x":528,"y":198,"width":32,"height":32},{"name":"silver-A-pushed","x":528,"y":231,"width":32,"height":32},{"name":"silver-!arrowdown","x":528,"y":264,"width":32,"height":32},{"name":"silver-!arrowdown-pushed","x":528,"y":297,"width":32,"height":32},{"name":"silver-!arrowleft","x":528,"y":330,"width":32,"height":32},{"name":"silver-!arrowleft-pushed","x":528,"y":363,"width":32,"height":32},{"name":"silver-!arrowright","x":528,"y":396,"width":32,"height":32},{"name":"silver-!arrowright-pushed","x":528,"y":429,"width":32,"height":32},{"name":"silver-!arrowup","x":528,"y":462,"width":32,"height":32},{"name":"silver-!arrowup-pushed","x":528,"y":495,"width":32,"height":32},{"name":"silver-B","x":528,"y":528,"width":32,"height":32},{"name":"silver-!blank","x":0,"y":561,"width":32,"height":32},{"name":"silver-blank-pushed","x":33,"y":561,"width":32,"height":32},{"name":"silver-B-pushed","x":66,"y":561,"width":32,"height":32},{"name":"silver-C","x":99,"y":561,"width":32,"height":32},{"name":"silver-C-pushed","x":132,"y":561,"width":32,"height":32},{"name":"silver-D","x":165,"y":561,"width":32,"height":32},{"name":"silver-D-pushed","x":198,"y":561,"width":32,"height":32},{"name":"silver-E","x":231,"y":561,"width":32,"height":32},{"name":"silver-E-pushed","x":264,"y":561,"width":32,"height":32},{"name":"silver-F","x":297,"y":561,"width":32,"height":32},{"name":"silver-F-pushed","x":330,"y":561,"width":32,"height":32},{"name":"silver-G","x":363,"y":561,"width":32,"height":32},{"name":"silver-G-pushed","x":396,"y":561,"width":32,"height":32},{"name":"silver-H","x":429,"y":561,"width":32,"height":32},{"name":"silver-H-pushed","x":462,"y":561,"width":32,"height":32},{"name":"silver-I","x":495,"y":561,"width":32,"height":32},{"name":"silver-I-pushed","x":528,"y":561,"width":32,"height":32},{"name":"silver-J","x":561,"y":0,"width":32,"height":32},{"name":"silver-J-pushed","x":561,"y":33,"width":32,"height":32},{"name":"silver-K","x":561,"y":66,"width":32,"height":32},{"name":"silver-K-pushed","x":561,"y":99,"width":32,"height":32},{"name":"silver-L","x":561,"y":132,"width":32,"height":32},{"name":"silver-L-pushed","x":561,"y":165,"width":32,"height":32},{"name":"silver-M","x":561,"y":198,"width":32,"height":32},{"name":"silver-M-pushed","x":561,"y":231,"width":32,"height":32},{"name":"silver-N","x":561,"y":264,"width":32,"height":32},{"name":"silver-N-pushed","x":561,"y":297,"width":32,"height":32},{"name":"silver-O","x":561,"y":330,"width":32,"height":32},{"name":"silver-O-pushed","x":561,"y":363,"width":32,"height":32},{"name":"silver-P","x":561,"y":396,"width":32,"height":32},{"name":"silver-P-pushed","x":561,"y":429,"width":32,"height":32},{"name":"silver-Q","x":561,"y":462,"width":32,"height":32},{"name":"silver-Q-pushed","x":561,"y":495,"width":32,"height":32},{"name":"silver-R","x":561,"y":528,"width":32,"height":32},{"name":"silver-R-pushed","x":561,"y":561,"width":32,"height":32},{"name":"silver-S","x":0,"y":594,"width":32,"height":32},{"name":"silver-S-pushed","x":33,"y":594,"width":32,"height":32},{"name":"silver-!square","x":66,"y":594,"width":32,"height":32},{"name":"silver-square-pushed","x":99,"y":594,"width":32,"height":32},{"name":"silver-T","x":132,"y":594,"width":32,"height":32},{"name":"silver-T-pushed","x":165,"y":594,"width":32,"height":32},{"name":"silver-!triangle","x":198,"y":594,"width":32,"height":32},{"name":"silver-triangle-pushed","x":231,"y":594,"width":32,"height":32},{"name":"silver-U","x":264,"y":594,"width":32,"height":32},{"name":"silver-U-pushed","x":297,"y":594,"width":32,"height":32},{"name":"silver-V","x":330,"y":594,"width":32,"height":32},{"name":"silver-V-pushed","x":363,"y":594,"width":32,"height":32},{"name":"silver-W","x":396,"y":594,"width":32,"height":32},{"name":"silver-W-pushed","x":429,"y":594,"width":32,"height":32},{"name":"silver-X","x":462,"y":594,"width":32,"height":32},{"name":"silver-X-pushed","x":495,"y":594,"width":32,"height":32},{"name":"silver-Y","x":528,"y":594,"width":32,"height":32},{"name":"silver-Y-pushed","x":561,"y":594,"width":32,"height":32},{"name":"silver-Z","x":594,"y":0,"width":32,"height":32},{"name":"silver-Z-pushed","x":594,"y":33,"width":32,"height":32},{"name":"yellow-0","x":594,"y":66,"width":32,"height":32},{"name":"yellow-0-pushed","x":594,"y":99,"width":32,"height":32},{"name":"yellow-1","x":594,"y":132,"width":32,"height":32},{"name":"yellow-1-pushed","x":594,"y":165,"width":32,"height":32},{"name":"yellow-2","x":594,"y":198,"width":32,"height":32},{"name":"yellow-2-pushed","x":594,"y":231,"width":32,"height":32},{"name":"yellow-3","x":594,"y":264,"width":32,"height":32},{"name":"yellow-3-pushed","x":594,"y":297,"width":32,"height":32},{"name":"yellow-4","x":594,"y":330,"width":32,"height":32},{"name":"yellow-4-pushed","x":594,"y":363,"width":32,"height":32},{"name":"yellow-5","x":594,"y":396,"width":32,"height":32},{"name":"yellow-5-pushed","x":594,"y":429,"width":32,"height":32},{"name":"yellow-6","x":594,"y":462,"width":32,"height":32},{"name":"yellow-6-pushed","x":594,"y":495,"width":32,"height":32},{"name":"yellow-7","x":594,"y":528,"width":32,"height":32},{"name":"yellow-7-pushed","x":594,"y":561,"width":32,"height":32},{"name":"yellow-8","x":594,"y":594,"width":32,"height":32},{"name":"yellow-8-pushed","x":0,"y":627,"width":32,"height":32},{"name":"yellow-9","x":33,"y":627,"width":32,"height":32},{"name":"yellow-9-pushed","x":66,"y":627,"width":32,"height":32},{"name":"yellow-A","x":99,"y":627,"width":32,"height":32},{"name":"yellow-A-pushed","x":132,"y":627,"width":32,"height":32},{"name":"yellow-!arrowdown","x":165,"y":627,"width":32,"height":32},{"name":"yellow-!arrowdown-pushed","x":198,"y":627,"width":32,"height":32},{"name":"yellow-!arrowleft","x":231,"y":627,"width":32,"height":32},{"name":"yellow-!arrowleft-pushed","x":264,"y":627,"width":32,"height":32},{"name":"yellow-!arrowright","x":297,"y":627,"width":32,"height":32},{"name":"yellow-!arrowright-pushed","x":330,"y":627,"width":32,"height":32},{"name":"yellow-!arrowup","x":363,"y":627,"width":32,"height":32},{"name":"yellow-!arrowup-pushed","x":396,"y":627,"width":32,"height":32},{"name":"yellow-B","x":429,"y":627,"width":32,"height":32},{"name":"yellow-!blank","x":462,"y":627,"width":32,"height":32},{"name":"yellow-blank-pushed","x":495,"y":627,"width":32,"height":32},{"name":"yellow-B-pushed","x":528,"y":627,"width":32,"height":32},{"name":"yellow-C","x":561,"y":627,"width":32,"height":32},{"name":"yellow-C-pushed","x":594,"y":627,"width":32,"height":32},{"name":"yellow-D","x":627,"y":0,"width":32,"height":32},{"name":"yellow-D-pushed","x":627,"y":33,"width":32,"height":32},{"name":"yellow-E","x":627,"y":66,"width":32,"height":32},{"name":"yellow-E-pushed","x":627,"y":99,"width":32,"height":32},{"name":"yellow-F","x":627,"y":132,"width":32,"height":32},{"name":"yellow-F-pushed","x":627,"y":165,"width":32,"height":32},{"name":"yellow-G","x":627,"y":198,"width":32,"height":32},{"name":"yellow-G-pushed","x":627,"y":231,"width":32,"height":32},{"name":"yellow-H","x":627,"y":264,"width":32,"height":32},{"name":"yellow-H-pushed","x":627,"y":297,"width":32,"height":32},{"name":"yellow-I","x":627,"y":330,"width":32,"height":32},{"name":"yellow-I-pushed","x":627,"y":363,"width":32,"height":32},{"name":"yellow-J","x":627,"y":396,"width":32,"height":32},{"name":"yellow-J-pushed","x":627,"y":429,"width":32,"height":32},{"name":"yellow-K","x":627,"y":462,"width":32,"height":32},{"name":"yellow-K-pushed","x":627,"y":495,"width":32,"height":32},{"name":"yellow-L","x":627,"y":528,"width":32,"height":32},{"name":"yellow-L-pushed","x":627,"y":561,"width":32,"height":32},{"name":"yellow-M","x":627,"y":594,"width":32,"height":32},{"name":"yellow-M-pushed","x":627,"y":627,"width":32,"height":32},{"name":"yellow-N","x":0,"y":660,"width":32,"height":32},{"name":"yellow-N-pushed","x":33,"y":660,"width":32,"height":32},{"name":"yellow-O","x":66,"y":660,"width":32,"height":32},{"name":"yellow-O-pushed","x":99,"y":660,"width":32,"height":32},{"name":"yellow-P","x":132,"y":660,"width":32,"height":32},{"name":"yellow-P-pushed","x":165,"y":660,"width":32,"height":32},{"name":"yellow-Q","x":198,"y":660,"width":32,"height":32},{"name":"yellow-Q-pushed","x":231,"y":660,"width":32,"height":32},{"name":"yellow-R","x":264,"y":660,"width":32,"height":32},{"name":"yellow-R-pushed","x":297,"y":660,"width":32,"height":32},{"name":"yellow-S","x":330,"y":660,"width":32,"height":32},{"name":"yellow-S-pushed","x":363,"y":660,"width":32,"height":32},{"name":"yellow-!square","x":396,"y":660,"width":32,"height":32},{"name":"yellow-square-pushed","x":429,"y":660,"width":32,"height":32},{"name":"yellow-T","x":462,"y":660,"width":32,"height":32},{"name":"yellow-T-pushed","x":495,"y":660,"width":32,"height":32},{"name":"yellow-!triangle","x":528,"y":660,"width":32,"height":32},{"name":"yellow-triangle-pushed","x":561,"y":660,"width":32,"height":32},{"name":"yellow-U","x":594,"y":660,"width":32,"height":32},{"name":"yellow-U-pushed","x":627,"y":660,"width":32,"height":32},{"name":"yellow-V","x":660,"y":0,"width":32,"height":32},{"name":"yellow-V-pushed","x":660,"y":33,"width":32,"height":32},{"name":"yellow-W","x":660,"y":66,"width":32,"height":32},{"name":"yellow-W-pushed","x":660,"y":99,"width":32,"height":32},{"name":"yellow-X","x":660,"y":132,"width":32,"height":32},{"name":"yellow-X-pushed","x":660,"y":165,"width":32,"height":32},{"name":"yellow-Y","x":660,"y":198,"width":32,"height":32},{"name":"yellow-Y-pushed","x":660,"y":231,"width":32,"height":32},{"name":"yellow-Z","x":660,"y":264,"width":32,"height":32},{"name":"yellow-Z-pushed","x":660,"y":297,"width":32,"height":32}]